<?xml version="1.0" encoding="UTF-8"?>
<objects serializationModel="Studio.02.02.00">
	<object class="AudioFile" id="{d7884266-7f78-4384-9ded-776c3eda5951}">
		<property name="assetPath">
			<value>ShootTrials/Weapon_Submachine_Gun_Gunshots_3_Distant.WAV</value>
		</property>
		<property name="frequencyInKHz">
			<value>44.0999985</value>
		</property>
		<property name="channelCount">
			<value>2</value>
		</property>
		<property name="length">
			<value>1.6875056689342403</value>
		</property>
		<relationship name="masterAssetFolder">
			<destination>{51130421-aaf5-4ab8-b040-4641f2b20e10}</destination>
		</relationship>
	</object>
</objects>
